{"stats":{"minecraft:mined":{"minecraft:dark_oak_planks":5,"create:zinc_ore":70,"biomesoplenty:spanish_moss":16,"minecraft:white_bed":2,"farmersdelight:onions":5,"minecraft:oak_sapling":3,"minecraft:farmland":80,"thermal:cinnabar_ore":2,"thermal:ruby_ore":5,"farmersdelight:wild_carrots":9,"minecraft:dark_oak_log":31,"biomesoplenty:bush":1,"minecraft:grass_block":128,"randomium:randomium_ore":1,"occultism:datura":6,"minecraft:kelp":64,"farmersdelight:wild_onions":3,"minecraft:tall_seagrass":5,"minecraft:carrots":20,"minecraft:furnace":7,"minecraft:iron_ore":36,"desolation:charred_branches":1,"minecraft:andesite":92,"create:copper_ore":92,"minecraft:potatoes":12,"biomesoplenty:barley":27,"minecraft:stone":240,"desolation:ash_block_10":1,"minecraft:kelp_plant":53,"minecraft:clay":37,"minecraft:cornflower":3,"minecraft:crafting_table":4,"minecraft:torch":1,"minecraft:poppy":9,"minecraft:chest":3,"minecraft:andesite_wall":1,"minecraft:mushroom_stem":2,"minecraft:tall_grass":8,"minecraft:sugar_cane":47,"minecraft:diorite":7,"minecraft:seagrass":1,"biomesoplenty:goldenrod":1,"farmersdelight:wild_beetroots":1,"biomesoplenty:spanish_moss_plant":4,"desolation:scorched_tuft_glowing":1,"minecraft:wheat":84,"farmersdelight:rice_upper_crop":2,"minecraft:grass":211,"minecraft:coal_ore":57,"minecraft:oak_log":265,"minecraft:gravel":1,"minecraft:dirt":53,"thermal:nickel_ore":2,"minecraft:red_mushroom_block":36,"minecraft:oak_leaves":68},"minecraft:dropped":{"minecraft:water_bucket":1,"create:copper_ingot":10,"occultism:datura_seeds":2,"minecraft:wheat_seeds":15,"minecraft:oak_log":288,"minecraft:glass_bottle":2,"minecraft:cobblestone":18,"minecraft:andesite_wall":1,"exoticbirds:cooked_birdmeat":3,"minecraft:leather":2,"create:andesite_cobblestone":1,"minecraft:red_wool":5,"exoticbirds:mystery_egg":25,"minecraft:coal":144,"minecraft:red_mushroom":18,"minecraft:stick":1,"minecraft:pufferfish":3,"minecraft:dirt":6,"minecraft:dark_oak_log":3,"biomesoplenty:goldenrod":3,"minecraft:cornflower":2,"minecraft:cooked_cod":5,"aquaculture:atlantic_herring":1,"minecraft:cooked_salmon":2,"minecraft:heart_of_the_sea":5,"tconstruct:greenheart_log":36,"minecraft:dark_oak_planks":6,"minecraft:bucket":1,"minecraft:fishing_rod":5,"create:diorite_cobblestone":3,"tconstruct:earth_congealed_slime":10,"thermal:ice_charge":5,"minecraft:gold_ingot":30,"minecraft:bone":3,"minecraft:dark_oak_door":12,"minecraft:kelp":748,"minecraft:sugar_cane":31,"minecraft:bowl":1,"minecraft:chicken":3,"forbidden_arcanus:edelwood_log":10,"minecraft:oak_planks":1,"minecraft:carrot":2,"create:crushed_iron_ore":1,"buddycards:grading_sleeve":24,"buddycards:buddybeans":12,"exoticbirds:pigeon_egg":1,"tconstruct:earth_slime_sapling":5,"minecraft:slime_ball":65,"create:crushed_copper_ore":105,"minecraft:stone_pickaxe":12,"moreminecarts:wooden_rail":3,"thermal:silver_coin":1},"minecraft:killed":{"exoticbirds:pelican":4,"minecraft:spider":2,"minecraft:slime":7,"exoticbirds:crane":1,"minecraft:skeleton":6,"minecraft:chicken":4,"aquaculture:atlantic_herring":1,"aquaculture:jellyfish":2,"minecraft:creeper":3,"minecraft:sheep":5,"exoticbirds:flamingo":1,"minecraft:zombie":4,"exoticbirds:swan":2,"minecraft:cow":1},"minecraft:picked_up":{"minecraft:fishing_rod":6,"create:crushed_copper_ore":245,"minecraft:crafting_table":4,"minecraft:allium":5,"minecraft:wheat":76,"minecraft:chicken":3,"exoticbirds:pigeon_egg":1,"buddycards:grading_sleeve":28,"thermal:cinnabar":3,"chisel:metals/bronze/badgreggy":1,"farmersdelight:rice_panicle":2,"minecraft:cornflower":6,"minecraft:string":3,"minecraft:cooked_salmon":5,"exoticbirds:crane_egg":1,"minecraft:pufferfish":3,"biomesoplenty:spanish_moss":24,"minecraft:beef":3,"minecraft:iron_nugget":4,"minecraft:poppy":8,"minecraft:light_gray_wool":7,"minecraft:minecart":3,"minecraft:sugar_cane":75,"minecraft:chest":3,"minecraft:phantom_membrane":1,"minecraft:furnace":7,"minecraft:dark_oak_door":14,"minecraft:stick":59,"create:crushed_nickel_ore":2,"minecraft:torch":2,"minecraft:dried_kelp":4,"minecraft:carrot":81,"minecraft:dark_oak_planks":9,"minecraft:andesite_wall":1,"tconstruct:earth_congealed_slime":12,"minecraft:arrow":10,"minecraft:cooked_cod":6,"minecraft:tropical_fish":6,"minecraft:beetroot_seeds":1,"farmersdelight:onion":21,"extcaves:pebble_stone":3,"occultism:datura":5,"minecraft:gold_ingot":36,"tconstruct:earth_slime_sapling":7,"minecraft:mutton":9,"create:andesite_cobblestone":99,"minecraft:cod":13,"exoticbirds:raw_birdmeat":17,"minecraft:white_wool":4,"minecraft:cobblestone":282,"desolation:scorched_tuft_glowing":1,"create:mossy_weathered_limestone":1,"occultism:datura_seeds":21,"minecraft:feather":13,"minecraft:water_bucket":1,"tconstruct:greenheart_log":42,"minecraft:salmon":15,"biomesoplenty:goldenrod":3,"minecraft:leather":2,"minecraft:red_mushroom":18,"minecraft:potato":44,"create:weathered_limestone_cobblestone":4,"minecraft:oak_log":301,"create:andesite_alloy":1,"minecraft:gunpowder":2,"thermal:ice_charge":6,"minecraft:dirt":255,"minecraft:paper":16,"create:copper_ingot":12,"minecraft:bone":8,"minecraft:apple":8,"minecraft:kelp":1143,"minecraft:wheat_seeds":276,"minecraft:heart_of_the_sea":6,"minecraft:iron_ingot":11,"minecraft:stone_pickaxe":14,"create:crushed_zinc_ore":74,"minecraft:glass_bottle":1,"aquaculture:atlantic_herring":1,"aquaculture:jellyfish":1,"moreminecarts:wooden_rail":6,"xreliquary:slime_pearl":1,"create:diorite_cobblestone":7,"exoticbirds:swan_egg":1,"minecraft:red_wool":6,"minecraft:gravel":2,"buddycards:buddybeans":18,"minecraft:white_bed":2,"exoticbirds:mystery_egg":30,"minecraft:dark_oak_log":29,"rubber_duck:rubber_duck_item":1,"forbidden_arcanus:edelwood_log":12,"minecraft:slime_ball":83,"create:crushed_iron_ore":48,"thermal:ruby":5,"minecraft:oak_sapling":105,"minecraft:coal":312,"minecraft:clay_ball":140},"minecraft:broken":{"minecraft:stone_pickaxe":2,"minecraft:stone_axe":2,"minecraft:iron_pickaxe":1,"minecraft:stone_shovel":1},"minecraft:killed_by":{"minecraft:drowned":1},"minecraft:crafted":{"minecraft:oak_planks":16,"minecraft:stone_shovel":2,"minecraft:dark_oak_boat":1,"minecraft:iron_nugget":90,"minecraft:cooked_chicken":3,"minecraft:furnace":2,"minecraft:cooked_mutton":16,"create:copper_nugget":18,"minecraft:slime_ball":24,"minecraft:stone_pickaxe":2,"farmersdelight:rice":2,"minecraft:dark_oak_planks":104,"minecraft:stone_hoe":1,"minecraft:cooked_beef":1,"minecraft:red_dye":3,"minecraft:cooked_cod":6,"minecraft:crafting_table":1,"minecraft:dried_kelp":64,"minecraft:wooden_pickaxe":1,"minecraft:red_wool":1,"minecraft:cooked_salmon":1,"minecraft:bucket":1,"minecraft:stone_axe":3,"minecraft:air":0,"minecraft:stick":28,"minecraft:iron_ingot":10,"minecraft:iron_pickaxe":1,"minecraft:stone_sword":1,"exoticbirds:cooked_birdmeat":26,"minecraft:white_bed":1,"minecraft:torch":36},"minecraft:used":{"minecraft:stone_sword":108,"exoticbirds:swan_egg":1,"minecraft:tropical_fish":6,"minecraft:stone_shovel":231,"minecraft:dried_kelp":3,"minecraft:poppy":5,"minecraft:chest":3,"minecraft:cooked_salmon":4,"minecraft:stone_hoe":80,"minecraft:cooked_chicken":3,"minecraft:torch":42,"minecraft:dirt":217,"buddycards:buddybeans":1,"minecraft:carrot":94,"minecraft:allium":5,"minecraft:dark_oak_planks":79,"create:builders_tea":2,"minecraft:dark_oak_boat":1,"minecraft:oak_sapling":42,"minecraft:furnace":10,"minecraft:cooked_cod":4,"minecraft:minecart":3,"minecraft:cooked_beef":1,"minecraft:potato":56,"minecraft:wheat_seeds":166,"minecraft:cooked_mutton":6,"minecraft:water_bucket":60,"minecraft:stone_pickaxe":347,"occultism:datura_seeds":19,"minecraft:wooden_pickaxe":16,"minecraft:sugar_cane":16,"farmersdelight:onion":23,"supplementaries:bomb":3,"minecraft:crafting_table":5,"minecraft:white_bed":3,"occultism:datura":1,"farmersdelight:rice":4,"minecraft:oak_log":3,"minecraft:flower_pot":1,"minecraft:cornflower":4,"farmersdelight:apple_cider":1,"minecraft:dark_oak_log":7,"minecraft:iron_pickaxe":250,"minecraft:suspicious_stew":1,"minecraft:gravel":2,"minecraft:stone_axe":353,"exoticbirds:cooked_birdmeat":23,"minecraft:cobblestone":4,"rubber_duck:rubber_duck_item":1,"minecraft:bucket":60,"minecraft:kelp":183,"minecraft:writable_book":3},"minecraft:custom":{"lootr:looted_stat":2,"minecraft:mob_kills":44,"minecraft:animals_bred":3,"minecraft:interact_with_crafting_table":28,"minecraft:leave_game":8,"minecraft:time_since_death":219147,"minecraft:climb_one_cm":6525,"minecraft:sprint_one_cm":499324,"minecraft:walk_one_cm":326852,"minecraft:drop":444,"minecraft:deaths":1,"minecraft:sneak_time":22561,"minecraft:walk_under_water_one_cm":59224,"minecraft:boat_one_cm":372078,"minecraft:jump":2043,"minecraft:walk_on_water_one_cm":66100,"minecraft:interact_with_furnace":97,"minecraft:play_one_minute":224866,"minecraft:pot_flower":1,"minecraft:sleep_in_bed":12,"minecraft:time_since_rest":771,"minecraft:damage_taken":1789,"minecraft:minecart_one_cm":14293,"minecraft:damage_dealt":4836,"minecraft:swim_one_cm":105534,"minecraft:player_kills":1,"minecraft:fly_one_cm":398256,"minecraft:open_chest":64,"minecraft:crouch_one_cm":66159,"minecraft:fall_one_cm":36702}},"DataVersion":2586}